<?xml version="1.0" encoding="utf-8" ?>
<dwsync>
<file name="editor_plugin.js" server="ftp.garland-online.co.uk/public_html/" local="129397427687035282" remote="129397507800000000" />
<file name="editor_plugin_src.js" server="ftp.garland-online.co.uk/public_html/" local="129397427687485327" remote="129397507800000000" />
<file name="example.html" server="ftp.garland-online.co.uk/public_html/" local="129397427687985377" remote="129397507800000000" />
<file name="preview.html" server="ftp.garland-online.co.uk/public_html/" local="129397427688475426" remote="129397507800000000" />
<file name="editor_plugin.js" server="ftp.nicetri.co.uk/httpdocs/" local="129397427687035282" remote="129397602600000000" />
<file name="editor_plugin_src.js" server="ftp.nicetri.co.uk/httpdocs/" local="129397427687485327" remote="129397602600000000" />
<file name="example.html" server="ftp.nicetri.co.uk/httpdocs/" local="129397427687985377" remote="129397602600000000" />
<file name="preview.html" server="ftp.nicetri.co.uk/httpdocs/" local="129397427688475426" remote="129397602600000000" />
<file name="editor_plugin.js" server="testphp//var/www/openentrysystem/" local="129397427687035282" remote="129532409460000000" />
<file name="editor_plugin_src.js" server="testphp//var/www/openentrysystem/" local="129397427687485327" remote="129532409460000000" />
<file name="example.html" server="testphp//var/www/openentrysystem/" local="129397427687985377" remote="129532409460000000" />
<file name="preview.html" server="testphp//var/www/openentrysystem/" local="129397427688475426" remote="129532409470000000" />
<file name="editor_plugin.js" server="ftp.openentrysystem.org/public_html/" local="129397427687035282" remote="129399312000000000" />
<file name="editor_plugin_src.js" server="ftp.openentrysystem.org/public_html/" local="129397427687485327" remote="129399312000000000" />
<file name="example.html" server="ftp.openentrysystem.org/public_html/" local="129397427687985377" remote="129399312000000000" />
<file name="preview.html" server="ftp.openentrysystem.org/public_html/" local="129397427688475426" remote="129399312000000000" />
<file name="editor_plugin.js" server="ftp.riversiderunnersraces.co.uk/public_html/" local="129397427687035282" remote="129410406000000000" />
<file name="editor_plugin_src.js" server="ftp.riversiderunnersraces.co.uk/public_html/" local="129397427687485327" remote="129410406000000000" />
<file name="example.html" server="ftp.riversiderunnersraces.co.uk/public_html/" local="129397427687985377" remote="129410406000000000" />
<file name="preview.html" server="ftp.riversiderunnersraces.co.uk/public_html/" local="129397427688475426" remote="129410406000000000" />
<file name="editor_plugin.js" server="ftp.openentrysystem.org//var/www/vhosts/ds9972.dedicated.turbodns.co.uk/openentrysystem.org/" local="129397427687035282" remote="130692826430000000" />
<file name="editor_plugin_src.js" server="ftp.openentrysystem.org//var/www/vhosts/ds9972.dedicated.turbodns.co.uk/openentrysystem.org/" local="129397427687485327" remote="130692826430000000" />
<file name="example.html" server="ftp.openentrysystem.org//var/www/vhosts/ds9972.dedicated.turbodns.co.uk/openentrysystem.org/" local="129397427687985377" remote="130692826430000000" />
<file name="preview.html" server="ftp.openentrysystem.org//var/www/vhosts/ds9972.dedicated.turbodns.co.uk/openentrysystem.org/" local="129397427688475426" remote="130692826450000000" />
<file name="editor_plugin.js" server="ftp.riversiderunnersraces.co.uk//var/www/vhosts/ds9972.dedicated.turbodns.co.uk/riversiderunnersraces.co.uk/" local="129397427687035282" remote="130694339890000000" />
<file name="editor_plugin_src.js" server="ftp.riversiderunnersraces.co.uk//var/www/vhosts/ds9972.dedicated.turbodns.co.uk/riversiderunnersraces.co.uk/" local="129397427687485327" remote="130694339910000000" />
<file name="example.html" server="ftp.riversiderunnersraces.co.uk//var/www/vhosts/ds9972.dedicated.turbodns.co.uk/riversiderunnersraces.co.uk/" local="129397427687985377" remote="130694339920000000" />
<file name="preview.html" server="ftp.riversiderunnersraces.co.uk//var/www/vhosts/ds9972.dedicated.turbodns.co.uk/riversiderunnersraces.co.uk/" local="129397427688475426" remote="130694339970000000" />
<file name="editor_plugin.js" server="ubuntu//var/www/html/oes/" local="130561596000000000" remote="130561596000000000" />
<file name="editor_plugin_src.js" server="ubuntu//var/www/html/oes/" local="130561596000000000" remote="130561596000000000" />
<file name="example.html" server="ubuntu//var/www/html/oes/" local="130561596000000000" remote="130561596000000000" />
<file name="preview.html" server="ubuntu//var/www/html/oes/" local="130561596000000000" remote="130561596000000000" />
</dwsync>